pyapp_ext/aiobotocore/__init__.py
pyapp_ext/aiobotocore/__version__.py
pyapp_ext/aiobotocore/checks.py
pyapp_ext/aiobotocore/default_settings.py
pyapp_ext/aiobotocore/factory.py
pyapp_ext/aiobotocore/queues.py
pyApp_AIOBotocore-1.2.0.dist-info/LICENSE
pyApp_AIOBotocore-1.2.0.dist-info/METADATA
pyApp_AIOBotocore-1.2.0.dist-info/WHEEL
pyApp_AIOBotocore-1.2.0.dist-info/entry_points.txt
pyApp_AIOBotocore-1.2.0.dist-info/top_level.txt
pyApp_AIOBotocore-1.2.0.dist-info/RECORD
